<?xml version="1.0" ?>
<annotation>
<folder>phone1</folder>
<filename>ph282.jpg</filename>
<path>D:\BaiduNetdiskDownload\抽烟打电话数据集\train\phone1\ph282.jpg</path>
<source>
    <database>Unknown</database>
</source>
<size>
    <width>612</width>
    <height>408</height>
    <depth>3</depth>
</size>

<segmented>0</segmented>
    <object>
    <name>face</name>
    <pose>Unspecified</pose>
    <truncated>0</truncated>
    <difficult>0</difficult>
    <bndbox>
        <xmin>302</xmin>
        <ymin>30</ymin>
        <xmax>384</xmax>
        <ymax>132</ymax>
    </bndbox>
</object>
    <object>
    <name>phone</name>
    <pose>Unspecified</pose>
    <truncated>0</truncated>
    <difficult>0</difficult>
    <bndbox>
        <xmin>170</xmin>
        <ymin>260</ymin>
        <xmax>206</xmax>
        <ymax>273</ymax>
    </bndbox>
</object>
</annotation>
