<?xml version="1.0" ?>
<annotation>
<folder>phone1</folder>
<filename>ph301.jpg</filename>
<path>D:\BaiduNetdiskDownload\抽烟打电话数据集\train\phone1\ph301.jpg</path>
<source>
    <database>Unknown</database>
</source>
<size>
    <width>612</width>
    <height>399</height>
    <depth>3</depth>
</size>

<segmented>0</segmented>
    <object>
    <name>phone</name>
    <pose>Unspecified</pose>
    <truncated>0</truncated>
    <difficult>0</difficult>
    <bndbox>
        <xmin>194</xmin>
        <ymin>144</ymin>
        <xmax>271</xmax>
        <ymax>280</ymax>
    </bndbox>
</object>
    <object>
    <name>face</name>
    <pose>Unspecified</pose>
    <truncated>0</truncated>
    <difficult>0</difficult>
    <bndbox>
        <xmin>434</xmin>
        <ymin>28</ymin>
        <xmax>516</xmax>
        <ymax>193</ymax>
    </bndbox>
</object>
</annotation>
