<?xml version="1.0" ?>
<annotation>
<folder>phone1</folder>
<filename>ph607.jpg</filename>
<path>D:\BaiduNetdiskDownload\抽烟打电话数据集\train\phone1\ph607.jpg</path>
<source>
    <database>Unknown</database>
</source>
<size>
    <width>139</width>
    <height>187</height>
    <depth>3</depth>
</size>

<segmented>0</segmented>
    <object>
    <name>face</name>
    <pose>Unspecified</pose>
    <truncated>0</truncated>
    <difficult>0</difficult>
    <bndbox>
        <xmin>36</xmin>
        <ymin>63</ymin>
        <xmax>103</xmax>
        <ymax>134</ymax>
    </bndbox>
</object>
    <object>
    <name>phone</name>
    <pose>Unspecified</pose>
    <truncated>0</truncated>
    <difficult>0</difficult>
    <bndbox>
        <xmin>30</xmin>
        <ymin>147</ymin>
        <xmax>66</xmax>
        <ymax>174</ymax>
    </bndbox>
</object>
</annotation>
